{"second_layer":"","max_quantity":0,"validate_access":false,"price_index":1,"open_time":"09:15:00","price_range":"","zone_id":935471,"eta":"30 min","eta_value":30,"popularity":0,"schedules":[{"open_time":"09:15:00","close_time":"21:45:00"}],"logo":"1306704528-1532532575.png","id":"1306704528_935471","store_id":1306704528,"only_prime":false,"index":43,"brand_name":"Carl's Jr","close_time":"21:45:00","store_type":"restaurant","version":0,"has_promise":false,"tags":[35054],"split_order":false,"layout_store_id":1306704513,"background":"1306704528-1532532576.png","friendly_url":{"friendly_url":"carl-s-jr","store_id":1306704528},"name":"Carl's Jr WTC","percentage_service_fee":0,"has_comments":true,"is_available":true,"delivery_price":40,"experiments":[],"discount_tags":[],"rating":{"store_id":1306704528,"score":4.4,"total_reviews":5576},"saturation":{"store_id":1306704528,"saturations":{"geographical":"none","store":"none"},"eta":{"value":30,"action":0},"price":{"value":0,"action":0},"switches":{"high_demand":0,"cash":1,"checkout_confirmation":0,"pos":1},"cooking_time":14,"distance":2000,"weight":{"value":0,"action":0}},"delivery_methods":["delivery"],"location":[-99.171906,19.39398],"friends_orders_count":0,"address":"Insurgentes Sur #682 Local A Col de Valle CP 03100 Deleg Benito Juarez CDMX","normalized_index":43,"normalized_old_index":43,"old_index":-95,"is_currently_available":true,"brand_id":196,"zone_size":6,"elastic_version":1569481200000,"complete_schedules":[{"day":"mon","open_time":"09:15:00","close_time":"21:45:00"},{"day":"tue","open_time":"09:15:00","close_time":"21:45:00"},{"day":"wed","open_time":"09:15:00","close_time":"21:45:00"},{"day":"thu","open_time":"09:15:00","close_time":"21:45:00"},{"day":"fri","open_time":"09:15:00","close_time":"21:45:00"},{"day":"sat","open_time":"09:15:00","close_time":"21:45:00"},{"day":"sun","open_time":"09:15:00","close_time":"21:45:00"},{"day":"hol","open_time":"09:15:00","close_time":"21:45:00"}],"is_enabled":true,"is_main":false,"is_exclusive":false,"is_open_today":true,"is_marketplace":false,"is_open":true,"meals":[{"name":"Crispy Chicken Salad","description":"Ensalada con dos chicken tenders preparados al ordenar sobre una mezcla de lechugas, tomate, cebolla morada, pepino y zanahoria rayada. Acompañados con queso, crotones.","price":139,"img":"https://images.rappi.com.mx/products/975241002-1503516041.png?d=200x200&e=webp"},{"name":"Charbroiled Chicken Salad","description":"Ensala de mezcla de lechugas con espinacas, pollo a la parrilla, queso rallado estilo americano, cebolla, tomate, pepinos. Acompáñela con el aderezo de su elección y sus ya tradicionales crotones.","price":125,"img":"https://images.rappi.com.mx/products/975241006-1547100462.png?d=200x200&e=webp"},{"name":"Papas a la Francesa ","description":"Escoge tus papas a la Francesa medianas o grandes.","price":39,"img":"https://images.rappi.com.mx/products/975241009-1547150104.png?d=200x200&e=webp"},{"name":"Papas Crisscut ","description":"Escoge tus crujientes papas fritas con corte crisscut medianas o grandes.","price":39,"img":"https://images.rappi.com.mx/products/975241010-1547150122.png?d=200x200&e=webp"},{"name":"Aros de Cebolla","description":"Escoge tus aros de cebolla medianos o grandes.","price":42,"img":"https://images.rappi.com.mx/products/975241012-1547150106.png?d=200x200&e=webp"},{"name":"Papas Chili Cheese","description":"Papas a la francesa con chile, quesos jack y cheddar.","price":89,"img":"https://images.rappi.com.mx/products/975241013-1547150105.png?d=200x200&e=webp"},{"name":"WESTERN BACON FRIES","description":"Papas a la francesa con el rico sabor de la WESTERN BACON CHEESEBURGER.","price":49,"img":"https://images.rappi.com.mx/products/976112669-1564770982360.png?d=200x200&e=webp"},{"name":"Chocolate Chip Cookie","description":"Galleta con chispas de chocolate.","price":33,"img":"https://images.rappi.com.mx/products/975241017-1547150121.png?d=200x200&e=webp"},{"name":"Cheescake de Oreo","description":"Pay de queso con oreo.","price":55,"img":"https://images.rappi.com.mx/products/975270917-1503516444.png?d=200x200&e=webp"},{"name":"Cheescake de Fresas","description":"Pay de queso con fresas.","price":55,"img":"https://images.rappi.com.mx/products/975270918-1547150128.png?d=200x200&e=webp"},{"name":"Cheesecake Hershey´s Cookies & Creme","description":"Pay de queso hershey´s cookies & creme.","price":55,"img":"https://images.rappi.com.mx/products/976079219-1559603033.png?d=200x200&e=webp"},{"name":"Refresco Grande","description":"Escoge tu refresco grande de 44 onzas con o sin azúcar. ","price":45,"img":"https://images.rappi.com.mx/products/975241019-1547150102.png?d=200x200&e=webp"},{"name":"Agua Embotellada","description":"Agua embotellada Ciel de 600 ml.","price":30,"img":"https://images.rappi.com.mx/products/975241021-1518762638.png?d=200x200&e=webp"},{"name":"Malteada de Vainilla","description":"Prueba nuestras deliciosas malteada de vainilla.","price":74,"img":"https://images.rappi.com.mx/products/975241023-1547150102.png?d=200x200&e=webp"},{"name":"Malteada de Chocolate","description":"Prueba nuestras deliciosas malteada de chocolate.","price":74,"img":"https://images.rappi.com.mx/products/975563028-1547150100.png?d=200x200&e=webp"},{"name":"Malteada de Fresa","description":"Prueba nuestras deliciosas malteada de fresa.","price":74,"img":"https://images.rappi.com.mx/products/975563057-1547150102.png?d=200x200&e=webp"},{"name":"Malteada de Oreo","description":"Prueba nuestra deliciosa malteada de oreo.","price":74,"img":"https://images.rappi.com.mx/products/975563120-1547150102.png?d=200x200&e=webp"},{"name":"Teriyaki Thickburger 1/2","description":"Hamburguesa de carne 100% angus, queso suizo, piña rebanada, salsa teriyaki, cebollas rojas, tomate, lechuga y mayonesa en bollo recién horneado.","price":149,"img":"https://images.rappi.com.mx/products/976092594-1563293566.png?d=200x200&e=webp"},{"name":"Teriyaki Thickburger 1/3\t","description":"Hamburguesa de carne 100% angus, queso suizo, piña rebanada, salsa teriyaki, cebollas rojas, tomate, lechuga y mayonesa en bollo recién horneado.","price":126,"img":"https://images.rappi.com.mx/products/975806219-1547150107.png?d=200x200&e=webp"},{"name":"Jalapeño Thickburger\t","description":"Hamburguesa de carne 100% de res black angus asada a la parrilla 1/3 lb con chiles jalapeños, queso pepper jack, cebolla, tomate, lechuga y salsa santa fe.","price":115,"img":"https://images.rappi.com.mx/products/975850809-1547149760.png?d=200x200&e=webp"},{"name":"Guacamole Bacon Thickburger","description":"Hamburguesa de carne 100% black angus asada a la parrilla, queso pepperjack, cebolla morada, lechuga, tomate, salsa Santa Fe y tocino.","price":132,"img":"https://images.rappi.com.mx/products/975240967-1547150126.png?d=200x200&e=webp"},{"name":"Low-Carb Thickburger","description":"Como \"the original thickburger\", pero con pepinillos y envuelta en lechuga en lugar de pan. 1/3 de libra.","price":109,"img":"https://images.rappi.com.mx/products/975240974-1547150124.png?d=200x200&e=webp"},{"name":"Portobello Mushroom Thickburger","description":"Hamburguesa con mayonesa, lechuga, tomate, cebolla morada, carne 100% black angus asada a la parrilla, queso suizo y exquisitos champiñones.","price":119,"img":"https://images.rappi.com.mx/products/975240971-1547150126.png?d=200x200&e=webp"},{"name":"Original Thickburger","description":"Hamburguesa con mostaza, catsup, carne 100% black angus asada a la parrilla, mostaza, catsup, queso americano, cebolla morada, tomate, lechuga y pepinillos.","price":115,"img":"https://images.rappi.com.mx/products/975240964-1547150125.png?d=200x200&e=webp"},{"name":"Western Bacon Thickburger","description":"Hamburguesa de carne 100% black angus asada a la parrilla, tiras de tocino, rebanadas de queso americano, aros de cebolla empanizados y salsa BBQ.","price":125,"img":"https://images.rappi.com.mx/products/975240969-1547150125.png?d=200x200&e=webp"},{"name":"Famous Star con Queso","description":"Hamburguesa de carne 100% de res asada a la parrilla, salsa especial, queso americano, mayonesa, lechuga, cebolla, tomate y pepinillos. ","price":79,"img":"https://images.rappi.com.mx/products/975240954-1559158281.png?d=200x200&e=webp"},{"name":"Super Star con Queso","description":"Hamburguesa de dos piezas de carne 100% de res asada a la parrilla, salsa especial, queso americano, mayonesa, lechuga, cebolla, tomate y pepinillos.","price":97,"img":"https://images.rappi.com.mx/products/975240955-1559158283.png?d=200x200&e=webp"},{"name":"Western Bacon Cheese Burger","description":"Hamburguesa de carne 100% de res asada a la parrilla, salsa BBQ, rebanadas de tocino, queso americano y aros de cebolla empanizados.","price":89,"img":"https://images.rappi.com.mx/products/975240957-1559158285.png?d=200x200&e=webp"},{"name":"Double Western Cheese Burger","description":"Hamburguesa de dos piezas de carne 100% de res asada a la parrilla, salsa BBQ, rebanadas de tocino, queso americano y aros de cebolla empanizados.","price":115,"img":"https://images.rappi.com.mx/products/975240959-1559158282.png?d=200x200&e=webp"},{"name":"Teriyaki Burger","description":"Hamburguesa de piña a la parrilla, salsa teriyaki, carne 100% de res a la parrilla, queso suizo, mayonesa, cebolla morada, tomate y lechuga.","price":87,"img":"https://images.rappi.com.mx/products/975240961-1559158285.png?d=200x200&e=webp"},{"name":"The Big Carl","description":"Hamburguesa de dos piezas de carne 100% de res asadas a la parrilla, nuestra salsa clásica, dos rebanadas de queso americano y lechuga.","price":97,"img":"https://images.rappi.com.mx/products/975240962-1559158285.png?d=200x200&e=webp"},{"name":"Guacamole Burger","description":"Hamburguesa de carne de res asada a la parrilla, queso pepperjack, cebolla morada, lechuga, tomate y salsa Santa Fe.","price":95,"img":"https://images.rappi.com.mx/products/975324574-1559158282.png?d=200x200&e=webp"},{"name":"Double Guacamole Burger","description":"Hamburguesa de dos piezas de carne de res asada a la parrilla, queso pepperjack, cebolla morada, lechuga, tomate y salsa Santa Fe.","price":119,"img":"https://images.rappi.com.mx/products/975324575-1559158281.png?d=200x200&e=webp"},{"name":"Famous Star con Queso","description":"Hamburguesa de carne 100% de res asada a la parrilla, salsa especial, queso americano, mayonesa, lechuga, cebolla, tomate y pepinillos. ","price":79,"img":"https://images.rappi.com.mx/products/975839725-1559158282.png?d=200x200&e=webp"},{"name":"Super Star con Queso","description":"Hamburguesa de dos piezas de carne 100% de res asada a la parrilla, salsa especial, queso americano, mayonesa, lechuga, cebolla, tomate y pepinillos.","price":97,"img":"https://images.rappi.com.mx/products/975839726-1559158283.png?d=200x200&e=webp"},{"name":"WESTERN BACON CHEESE BURGER","description":"Hamburguesa de carne 100% de res asada a la parrilla, salsa BBQ, rebanadas de tocino, queso americano y aros de cebolla empanizados.","price":89,"img":"https://images.rappi.com.mx/products/975839727-1559158285.png?d=200x200&e=webp"},{"name":"Combo Classic Burger","description":"Classic burger + papas a la francesa chicas.","price":99,"img":"https://images.rappi.com.mx/products/975857226-1559158281.png?d=200x200&e=webp"},{"name":"Double Deal","description":"1 hamburguesa famous star  + 1 western bacon + 2 papas a la francesa medianas.","price":189,"img":"https://images.rappi.com.mx/products/975858972-1559158282.png?d=200x200&e=webp"},{"name":"Triple Western Bacon Cheeseburger","description":"La nueva hamburguesa con queso triple western bacon lleva el sabor indulgente de esta hamburguesa clásica al siguiente nivel, que incluye tres carnes, cuatro rebanadas de tocino, queso americano derretido, aros de cebolla crujientes y una salsa BBQ.","price":189,"img":"https://images.rappi.com.mx/products/976112668-1564770982348.png?d=200x200&e=webp"},{"name":"Double Teriyaki Burger","description":"Hamburguesa de piña a la parrilla, salsa teriyaki, dos piezas de carne 100% de res a la parrilla, queso suizo, mayonesa, cebolla morada, tomate y lechuga.","price":107},{"name":"Big Chicken Fillet","description":"Hamburguesa de crujiente pechuga de pollo empanizada y sazonada con especias para darle un sabor único, con lechuga, tomate y mayonesa.","price":99,"img":"https://images.rappi.com.mx/products/976092540-1561574359752.png?d=200x200&e=webp"},{"name":"Charbroiled Chicken Club","description":"Hamburguesa de pechuga de pollo asada a la parrilla, mayonesa, tocino, queso estilo suizo, tomate y lechuga en pan integral.","price":109,"img":"https://images.rappi.com.mx/products/975240976-1547150125.png?d=200x200&e=webp"},{"name":"Santa Fe Chicken Club","description":"Hamburguesa de pechuga de pollo asada a la parrilla, salsa Santa Fe, queso estilo americano, chile verde y lechuga en pan integral.","price":99,"img":"https://images.rappi.com.mx/products/975240978-1547150125.png?d=200x200&e=webp"},{"name":"BBQ Chicken","description":"Hamburguesa de pechuga de pollo asada a la parrilla, salsa BBQ, tomate y lechuga en pan integral.","price":98,"img":"https://images.rappi.com.mx/products/975240979-1547150125.png?d=200x200&e=webp"},{"name":"Bacon Swiss Crispy Big Chicken Fillet","description":"Hamburguesa de crujiente pechuga de pollo empanizada y sazonada con especias, 2 piezas de tocino, queso suizo, lechuga, tomate y aderezo ranch.","price":109,"img":"https://images.rappi.com.mx/products/976092555-1561574359797.png?d=200x200&e=webp"},{"name":"Jalapeño Big Chicken Fillet","description":"Hamburguesa de crujiente pechuga de pollo empanizada y sazonada con especias, salsa Santa Fe, chile jalapeño, queso pepperjack, cebolla morada, tomate y lechuga.","price":99,"img":"https://images.rappi.com.mx/products/975240988-1532709382.png?d=200x200&e=webp"},{"name":"Jalapeño Chicken Tender Sándwich","description":"Hamburguesa de dos hand breaded chicken tenders™, aderezo santa fe, rodajas de chiles jalapeños, queso pepperjack, cebolla morada, lechuga y tomate en pan blanco.","price":79,"img":"https://images.rappi.com.mx/products/975240993-1547150124.png?d=200x200&e=webp"},{"name":"Chicken Tenders","description":"Crujientes tenders. ","price":79,"img":"https://images.rappi.com.mx/products/975240995-1547150105.png?d=200x200&e=webp"},{"name":"Estrellitas de Pollo","description":"Estrellitas de Pollo.","price":59,"img":"https://images.rappi.com.mx/products/975240999-1547150104.png?d=200x200&e=webp"},{"name":"Pancakes Platter","description":"Tres pancakes acompañados con tu elección de jamón, salchicha o bacon. Disponible hasta las 12 p.m.","price":65,"img":"https://images.rappi.com.mx/products/975270932-1547150105.png?d=200x200&e=webp"},{"name":"Burrito Americano ","description":"Prueba este delicioso burrito americano. Disponible hasta las 12 p.m.","price":65,"img":"https://images.rappi.com.mx/products/975270929-1547150105.png?d=200x200&e=webp"},{"name":"Hash Brown ","description":"17 Piezas de crujientes ruedas de papas frita . Disponible hasta las 12 p.m.","price":35,"img":"https://images.rappi.com.mx/products/975270930-1547150103.png?d=200x200&e=webp"},{"name":"Breakfast Burger","description":"Hamburguesa de torta de carne 100% de res asada a la parrilla, huevo, bacon, queso americano, hash brown nuggets y cátsup en pan con ajonjolí. Disponible hasta las 12 p.m.","price":89,"img":"https://images.rappi.com.mx/products/975270923-1547150129.png?d=200x200&e=webp"},{"name":"Breakfast Sándwich","description":"Sándwich con huevo, jamón, quesos americano y suizo derretidos en dos rebanadas de pan sourdough tostado. Disponible hasta las 12 p.m.","price":79,"img":"https://images.rappi.com.mx/products/975270926-1547150129.png?d=200x200&e=webp"},{"name":"Loaded Breakfast Burrito","description":"Burrito con huevo revuelto, salchicha, jamón, trocitos de bacon, hash brown nuggets, quesos jack y cheddar rallados y salsa fresca, todo envuelto en una tortilla de harina. Disponible hasta las 12 p.m.","price":69,"img":"https://images.rappi.com.mx/products/975270927-1547150105.png?d=200x200&e=webp"},{"name":"Deluxe Platter","description":"Huevo revuelto, gallo pinto y tu elección de jamón, salchicha o bacon acompañados con pan tostado. Disponible hasta las 12 p.m.","price":89}]}