{"second_layer":"frutosprohibidos-home1-1569451237009.png","max_quantity":0,"validate_access":false,"price_index":2,"open_time":"08:30:00","price_range":"","zone_id":962668,"eta":"35 min","eta_value":35,"popularity":0,"schedules":[{"open_time":"08:30:00","close_time":"21:30:00"}],"logo":"frutosprohibidos-logo-1-1567525044216.png","id":"1306710145_962668","store_id":1306710145,"only_prime":false,"index":32,"brand_name":"Frutos Prohibidos","close_time":"21:30:00","store_type":"restaurant","version":0,"has_promise":false,"tags":[35040,35054,35057],"split_order":false,"layout_store_id":990008239,"background":"frutosprohibidos-home-1-1567525045155.jpg","friendly_url":{"friendly_url":"frutos-prohibidos","store_id":1306710145},"name":"Frutos Prohibidos WTC","percentage_service_fee":0,"has_comments":true,"is_available":true,"delivery_price":40,"experiments":[],"discount_tags":[],"rating":{"store_id":1306710145,"score":4.2,"total_reviews":428},"saturation":{"store_id":1306710145,"saturations":{"geographical":"none","store":"none"},"eta":{"value":35,"action":0},"price":{"value":0,"action":0},"switches":{"high_demand":0,"cash":1,"checkout_confirmation":0,"pos":1},"cooking_time":24,"distance":2000,"weight":{"value":0,"action":0}},"delivery_methods":["delivery"],"location":[-99.17209,19.391676],"friends_orders_count":0,"address":"San Bernardino 21, Col del Valle Centro, 03100 Ciudad de México, CDMX","normalized_index":32,"normalized_old_index":32,"old_index":-103,"is_currently_available":true,"brand_id":426,"zone_size":6,"elastic_version":1569521683630,"complete_schedules":[{"day":"sat","open_time":"09:30:00","close_time":"18:30:00"},{"day":"sun","open_time":"09:30:00","close_time":"18:30:00"},{"day":"hol","open_time":"09:30:00","close_time":"18:30:00"},{"day":"mon","open_time":"08:30:00","close_time":"21:30:00"},{"day":"tue","open_time":"08:30:00","close_time":"21:30:00"},{"day":"wed","open_time":"08:30:00","close_time":"21:30:00"},{"day":"thu","open_time":"08:30:00","close_time":"21:30:00"},{"day":"fri","open_time":"08:30:00","close_time":"21:30:00"}],"is_enabled":true,"is_main":false,"is_exclusive":false,"is_open_today":true,"is_marketplace":false,"is_open":true,"meals":[{},{},{},{},{},{},{},{},{},{},{},{},{},{},{},{},{},{},{},{}]}