{"second_layer":"","max_quantity":0,"validate_access":false,"price_index":1,"open_time":"13:00:00","price_range":"","zone_id":1061683,"eta":"43 min","eta_value":43,"popularity":0,"schedules":[{"open_time":"13:00:00","close_time":"21:30:00"}],"logo":"los-villanos-logo1-1564152041907.png","id":"1306720409_1061683","store_id":1306720409,"only_prime":false,"index":50,"brand_name":"Taqueria Los Villanos","close_time":"21:30:00","store_type":"restaurant","version":0,"has_promise":false,"tags":[35049],"split_order":false,"layout_store_id":1306720409,"background":"portada-1565997042956.png","friendly_url":{"friendly_url":"taqueria-los-villanos","store_id":1306720409},"name":"Taqueria Los Villanos","percentage_service_fee":0,"has_comments":true,"is_available":true,"delivery_price":40,"experiments":[],"discount_tags":[],"rating":{"store_id":1306720409,"score":0,"total_reviews":0},"saturation":{"store_id":1306720409,"saturations":{"geographical":"none","store":"none"},"eta":{"value":43,"action":0},"price":{"value":0,"action":0},"switches":{"high_demand":0,"cash":1,"checkout_confirmation":0,"pos":1},"cooking_time":14,"distance":4000,"weight":{"value":0,"action":0}},"delivery_methods":["delivery"],"location":[-99.18822,19.433348],"friends_orders_count":0,"address":"Avenida Horacio 400, Polanco, Polanco V Secc, 11560 Ciudad de México, CDMX","normalized_index":50,"normalized_old_index":50,"old_index":-87,"is_currently_available":true,"brand_id":17706,"zone_size":9,"elastic_version":1569481200000,"complete_schedules":[{"day":"sat","open_time":"13:00:00","close_time":"21:30:00"},{"day":"hol","open_time":"13:30:00","close_time":"20:00:00"},{"day":"wed","open_time":"13:00:00","close_time":"21:30:00"},{"day":"thu","open_time":"13:00:00","close_time":"21:30:00"},{"day":"sun","open_time":"13:00:00","close_time":"19:00:00"},{"day":"fri","open_time":"00:01:00","close_time":"03:30:00"},{"day":"mon","open_time":"13:00:00","close_time":"21:30:00"},{"day":"tue","open_time":"13:00:00","close_time":"21:30:00"},{"day":"fri","open_time":"13:00:00","close_time":"21:30:00"},{"day":"sat","open_time":"00:01:00","close_time":"03:30:00"}],"is_enabled":false,"is_main":false,"is_exclusive":false,"is_open_today":true,"is_marketplace":false,"is_open":true,"meals":[{"name":"Combo Rappi","description":"Tres tacos a elegir + Frijoes Charros + Agua del día o Coca Cola","price":177.1,"img":"https://images.rappi.com.mx/products/976277835-1566253235.jpg?d=200x200&e=webp"},{"name":"Combo Cruda","description":"Escoge tres tacos + jugo de carne + Cerveza o Coca Cola","price":253,"img":"https://images.rappi.com.mx/products/976277850-1566253269.jpg?d=200x200&e=webp"},{"name":"Cebollitas Cambray Preparadas ","description":"Cebollitas cambray preparadas ","price":73,"img":"https://images.rappi.com.mx/products/976230338-1565996924806.png?d=200x200&e=webp"},{"name":"Queso de Aro ","description":"Queso de aro sellado con nopales a la mexicana ","price":91,"img":"https://images.rappi.com.mx/products/976230342-1565996924812.png?d=200x200&e=webp"},{"name":"Guacamole con Totopos de Pan Pita ","description":"Guacamole con totopos de pan pita ","price":85,"img":"https://images.rappi.com.mx/products/976230348-1565996924820.png?d=200x200&e=webp"},{"name":"Chicharrón de Queso ","description":"Chicharrón de queso ","price":85,"img":"https://images.rappi.com.mx/products/976230366-1565201225746.png?d=200x200&e=webp"},{"name":"Huarache Especial de Nopal ","description":"Huarache especial de nopal con carne y queso fresco","price":109,"img":"https://images.rappi.com.mx/products/976230369-1565996924828.png?d=200x200&e=webp"},{"name":"Jugo de Carne ","description":"Jugo de Carne ","price":73,"img":"https://images.rappi.com.mx/products/976230371-1565996924834.png?d=200x200&e=webp"},{"name":"Frijoles Charros ","description":"Frijoles charros ","price":48,"img":"https://images.rappi.com.mx/products/976230421-1565996924840.png?d=200x200&e=webp"},{"name":"Taco de Bistec ","description":"60 gr en tortilla de maíz hecha en casa ","price":40,"img":"https://images.rappi.com.mx/products/976230431-1565996924846.png?d=200x200&e=webp"},{"name":"Taco de Costilla ","description":"60 gr en tortilla de maíz hecha en casa ","price":45,"img":"https://images.rappi.com.mx/products/976230440-1565996924854.png?d=200x200&e=webp"},{"name":"Taco de Aguja","description":"60 gr en tortilla de maíz hecha en casa ","price":45,"img":"https://images.rappi.com.mx/products/976230441-1565996924860.png?d=200x200&e=webp"},{"name":"Taco de Arrachera ","description":"60 gr en tortilla de maíz hecha en casa ","price":52,"img":"https://images.rappi.com.mx/products/976230443-1565996924867.png?d=200x200&e=webp"},{"name":"Taco de Rib Eye","description":"60 gr en tortilla de maíz hecha en casa ","price":54,"img":"https://images.rappi.com.mx/products/976230445-1565996927386.png?d=200x200&e=webp"},{"name":"Taco de Cecina","description":"60 gr en tortilla de maíz hecha en casa ","price":48,"img":"https://images.rappi.com.mx/products/976230448-1565996927394.png?d=200x200&e=webp"},{"name":"Taco de Longaniza","description":"60 gr en tortilla de maíz hecha en casa ","price":30,"img":"https://images.rappi.com.mx/products/976230450-1565996927400.png?d=200x200&e=webp"},{"name":"Taco de Pechuga de Pollo ","description":"60 gr en tortilla de maíz hecha en casa ","price":42,"img":"https://images.rappi.com.mx/products/976230460-1565996927406.png?d=200x200&e=webp"},{"name":"Pastor","description":"60 gr en tortilla de maíz hecha en casa ","price":22,"img":"https://images.rappi.com.mx/products/976230464-1565996927419.png?d=200x200&e=webp"},{"name":"Picana","description":"60 gr en tortilla de maíz hecha en casa ","price":45,"img":"https://images.rappi.com.mx/products/976230471-1565996927425.png?d=200x200&e=webp"},{"name":"Gringas o Costras","description":"120 gr proteína + 40 gr de queso en tortilla de harina ","price":45,"img":"https://images.rappi.com.mx/products/976230474-1565996927432.png?d=200x200&e=webp"},{"name":"Los Hayes ","description":"100 gr proteína en pan pita ","price":76,"img":"https://images.rappi.com.mx/products/976230544-1565996927444.png?d=200x200&e=webp"},{"name":"Taco de Lengua ","description":"60 gr. en tortilla de maíz hecha en casa ","price":67,"img":"https://images.rappi.com.mx/products/976230570-1565996927453.png?d=200x200&e=webp"},{"name":"Taco de Suadero","description":"60 gr. en tortilla de maíz hecha en casa ","price":42,"img":"https://images.rappi.com.mx/products/976230575-1565996927461.png?d=200x200&e=webp"},{"name":"Taco de Chicharrón Prensado ","description":"60 gr. en tortilla de maíz hecha en casa ","price":30,"img":"https://images.rappi.com.mx/products/976230576-1565996929732.png?d=200x200&e=webp"},{"name":"Taco de Setas Adobadas ","description":"60 gr. en tortilla de maíz hecha en casa ","price":24,"img":"https://images.rappi.com.mx/products/976230577-1565996929739.png?d=200x200&e=webp"},{"name":"Taco de Suadero Campechano ","description":"60 gr. en tortilla de maíz hecha en casa ","price":35,"img":"https://images.rappi.com.mx/products/976230578-1565996929747.png?d=200x200&e=webp"},{"name":"Taco de Campechano de Cecina","description":"60 gr. en tortilla de maíz hecha en casa ","price":48,"img":"https://images.rappi.com.mx/products/976230579-1565996929755.png?d=200x200&e=webp"},{"name":"Taco de Bistec Periferico (120 Gr)","description":"60 gr. en tortilla de maíz hecha en casa ","price":91,"img":"https://images.rappi.com.mx/products/976230580-1565996929761.png?d=200x200&e=webp"},{"name":"Volcán de Pastor ","description":"60 gr. en tortillas de maíz hechas en casa + 20 gr de queso","price":58,"img":"https://images.rappi.com.mx/products/976230590-1565996929768.png?d=200x200&e=webp"},{"name":"Volcán de Pechuga de Pollo ","description":"60 gr. en tortillas de maíz hechas en casa + 20 gr de queso","price":67,"img":"https://images.rappi.com.mx/products/976230602-1565201231033.png?d=200x200&e=webp"},{"name":"Volcán de Bistec","description":"60 gr. en tortillas de maíz hechas en casa + 20 gr de queso","price":64},{"name":"Volcán de Costilla","description":"60 gr. en tortillas de maíz hechas en casa + 20 gr de queso","price":69},{"name":"Volcán de Aguja ","description":"60 gr. en tortillas de maíz hechas en casa + 20 gr de queso","price":69},{"name":"Volcán de Arrachera","description":"60 gr. en tortillas de maíz hechas en casa + 20 gr de queso","price":76},{"name":"Volcán de Rib Eye","description":"60 gr. en tortillas de maíz hechas en casa + 20 gr de queso","price":79},{"name":"Alambre de Setas ","description":"70 gr. en tortilla de maíz hecha en casa","price":30,"img":"https://images.rappi.com.mx/products/976230625-1565201235555.png?d=200x200&e=webp"},{"name":"Tinga de Zanahoria ","description":"70 gr. en tortilla de maíz hecha en casa","price":48,"img":"https://images.rappi.com.mx/products/976230626-1565201235563.png?d=200x200&e=webp"},{"name":"Jamaica Pibil","description":"70 gr. en tortilla de maíz hecha en casa","price":42,"img":"https://images.rappi.com.mx/products/976230631-1565996929775.png?d=200x200&e=webp"},{"name":"Campechano Vegano","description":"70 gr. en tortilla de maíz hecha en casa","price":48},{"name":"Huitlacoche con Hoja Santa ","description":"70 gr. en tortilla de maíz hecha en casa","price":54},{"name":"Especial ","description":"150 gr. chuleta, pastor, costilla y queso acompañados de tortilla de maíz con pimiento, tocino, cebolla y queso ","price":157},{"name":"Pastor","description":"150 gr. acompañados de tortilla de maíz con pimiento, tocino, cebolla y queso ","price":121},{"name":"Costilla ","description":"150 gr. acompañados de tortilla de maíz con pimiento, tocino, cebolla y queso ","price":139},{"name":"Aguja","description":"150 gr. acompañados de tortilla de maíz con pimiento, tocino, cebolla y queso ","price":139},{"name":"Rib Eye ","description":"150 gr. acompañados de tortilla de maíz con pimiento, tocino, cebolla y queso ","price":157},{"name":"Arrachera ","description":"150 gr. acompañados de tortilla de maíz con pimiento, tocino, cebolla y queso ","price":151},{"name":"Pollo","description":"150 gr. acompañados de tortilla de maíz con pimiento, tocino, cebolla y queso ","price":133},{"name":"Agua de Jamaica ","description":"Agua de jamaica ","price":42,"img":"https://images.rappi.com.mx/products/976230825-1565996929781.png?d=200x200&e=webp"},{"name":"Café Americano ","description":"Café americano ","price":48,"img":"https://images.rappi.com.mx/products/976230839-1565201235601.png?d=200x200&e=webp"},{"name":"Café Capuccino ","description":"Café capuccino ","price":54,"img":"https://images.rappi.com.mx/products/976230842-1565201235609.png?d=200x200&e=webp"},{"name":"Chocomilk ","description":"Chocomilk ","price":48,"img":"https://images.rappi.com.mx/products/976230843-1565201235617.png?d=200x200&e=webp"},{"name":"Agua del Día ","description":"Agua del día","price":42},{"name":"Kombucha Mi Amor 250 Ml","description":"Kombucha mi amor 250 ml ","price":73},{"name":"Refrescos 355 Ml","description":"Selecciona tu refresco de 355 ml ","price":36},{"name":"Chaparrita 250 Ml","description":"Chaparrita 250 ml ","price":30},{"name":"Agua Natural 600 Ml","description":"Agua natural 600 ml ","price":30},{"name":"Agua Mineral 355 Ml","description":"Agua mineral 355 ml ","price":36},{"name":"Acapulcoco ","description":"Acapulcoco ","price":61},{"name":"Café Expresso ","description":"Café expresso","price":48},{"name":"Chelato Villano ","description":"Chelato villano ","price":97,"img":"https://images.rappi.com.mx/products/976230816-1565201235586.png?d=200x200&e=webp"},{"name":"Cervezas 355 Ml","description":"Selecciona tu cerveza favorita 355 ml ","price":48},{"name":"Flan de Queso ","description":"Flan de queso ","price":79,"img":"https://images.rappi.com.mx/products/976230811-1565201235571.png?d=200x200&e=webp"},{"name":"Cheesecake de Queso Philadelphia con Yogurt ","description":"Cheesecake  de queso philadelphia con yogurt y galleta oreo","price":85,"img":"https://images.rappi.com.mx/products/976230814-1565201235579.png?d=200x200&e=webp"},{"name":"Crepas con Cajeta y Helado de Vainilla ","description":"Crepas con cajeta y helado de vainilla ","price":79},{"name":"Crepas con Chocolate y Helado de Vainilla ","description":"Crepas con chocolate y helado de vainilla ","price":79}]}